favorite_probability_distributions/Binomialdistribution.py
favorite_probability_distributions/Gaussiandistribution.py
favorite_probability_distributions/Generaldistribution.py
favorite_probability_distributions/__init__.py
favorite_probability_distributions-0.1.dist-info/DESCRIPTION.rst
favorite_probability_distributions-0.1.dist-info/METADATA
favorite_probability_distributions-0.1.dist-info/RECORD
favorite_probability_distributions-0.1.dist-info/WHEEL
favorite_probability_distributions-0.1.dist-info/metadata.json
favorite_probability_distributions-0.1.dist-info/top_level.txt
