Metadata-Version: 2.0
Name: favorite-probability-distributions
Version: 0.1
Summary: Includes all-time greatest hits like Gaussian and Binomial
Home-page: UNKNOWN
Author: UNKNOWN
Author-email: UNKNOWN
License: UNKNOWN
Platform: UNKNOWN
